Workbook

Sheet Settings
A1: Copilot Credits report
A3: Rate per Copilot Credit (USD) | B3: 0.01
A4: Report period - from | B4: 46289
A5: Report period - to | B5: 46295
A6: Tenant ID | B6: 00000000-0000-0000-0000-000000000000 (sample data - fictitious)
A7: Generated (UTC) | B7: 2026-10-01 00:00
A8: Script version | B8: 1.0.0
A10: Estimated Cost = Billed Credits x rate. Non-billable credits (for example Microsoft 365 Copilot licensed users or developer environments) cost nothing.
A11: Allocated Azure Cost = the billing policy's actual Azure charge for the day (or for the Microsoft 365 report window), split across report rows in proportion to their billed credits.
A12: Funding Source: PAYG = billed to the Azure subscription of the environment's billing policy. Prepaid, then PAYG = the environment has prepaid credits allocated and overflows to PAYG. Prepaid capacity = covered by capacity packs, no Azure charge. Non-billable = zero-rated usage.
A13: Microsoft 365 Copilot Chat rows come from the Copilot Credits report export and cover a 7- or 30-day window ending on 'Period End', not a single day.

Sheet Overview
A1: Credits and cost by product
A2: Product | B2: Billed Credits | C2: Non-billable Credits | D2: Credits Consumed | E2: Estimated Cost (USD) | F2: Allocated Azure Cost (USD)
A3: Copilot Studio | B3: =SUMIFS('Agent-User Daily'!$H$2:$H$8,'Agent-User Daily'!$M$2:$M$8,$A3) | C3: =SUMIFS('Agent-User Daily'!$I$2:$I$8,'Agent-User Daily'!$M$2:$M$8,$A3) | D3: =B3+C3 | E3: =SUMIFS('Agent-User Daily'!$F$2:$F$8,'Agent-User Daily'!$M$2:$M$8,$A3) | F3: =SUMIFS('Agent-User Daily'!$G$2:$G$8,'Agent-User Daily'!$M$2:$M$8,$A3)
A4: Microsoft 365 Copilot Chat (metered agents) | B4: =SUM('M365 Copilot Chat'!$F$2:$F$5) | C4: 0 | D4: =B4+C4 | E4: =SUM('M365 Copilot Chat'!$G$2:$G$5) | F4: =SUM('M365 Copilot Chat'!$H$2:$H$5)
A5: Total | B5: =SUM(B3:B4) | C5: =SUM(C3:C4) | D5: =SUM(D3:D4) | E5: =SUM(E3:E4) | F5: =SUM(F3:F4)
A7: Billed credits by funding source
A8: Funding Source | B8: Billed Credits | C8: Estimated Cost (USD) | D8: Allocated Azure Cost (USD)
A9: PAYG | B9: =SUMIFS('Agent-User Daily'!$H$2:$H$8,'Agent-User Daily'!$K$2:$K$8,$A9) | C9: =SUMIFS('Agent-User Daily'!$F$2:$F$8,'Agent-User Daily'!$K$2:$K$8,$A9) | D9: =SUMIFS('Agent-User Daily'!$G$2:$G$8,'Agent-User Daily'!$K$2:$K$8,$A9)
A10: Prepaid capacity | B10: =SUMIFS('Agent-User Daily'!$H$2:$H$8,'Agent-User Daily'!$K$2:$K$8,$A10) | C10: =SUMIFS('Agent-User Daily'!$F$2:$F$8,'Agent-User Daily'!$K$2:$K$8,$A10) | D10: =SUMIFS('Agent-User Daily'!$G$2:$G$8,'Agent-User Daily'!$K$2:$K$8,$A10)
A11: PAYG (Microsoft 365 billing policy) | B11: =SUM('M365 Copilot Chat'!$F$2:$F$5) | C11: =SUM('M365 Copilot Chat'!$G$2:$G$5) | D11: =SUM('M365 Copilot Chat'!$H$2:$H$5)
A12: Total | B12: =SUM(B9:B11) | C12: =SUM(C9:C11) | D12: =SUM(D9:D11)
A14: Azure actual charges on Copilot meters
A15: Azure cost (USD) | B15: =SUM('Reconciliation'!$E$3:$E$8)
A16: Azure quantity (credits) | B16: =SUM('Reconciliation'!$D$3:$D$8)
A17: Allocated to report rows (USD) | B17: =F5
A18: Not matched to any report row (USD) | B18: =B15-B17
A19: Unmatched cost usually means usage with no user (for example autonomous runs), a Microsoft 365 billing policy without --m365-policy-map, or metered usage this report doesn't cover.

Sheet Agent-User Daily
A1: Date | B1: Agent Name | C1: User | D1: Billing Policy | E1: Credits Consumed | F1: Estimated Cost (USD) | G1: Allocated Azure Cost (USD) | H1: Billed Credits | I1: Non-billable Credits | J1: Environment | K1: Funding Source | L1: Department | M1: Product | N1: Agent ID | O1: User ID | P1: Environment ID
A2: 46294 | B2: Finance Q&A | C2: dana@contoso.com | D2: (none) | E2: =H2+I2 | F2: =H2*Settings!$B$3 | G2: =IFERROR(SUMIFS('Reconciliation'!$E$3:$E$8,'Reconciliation'!$A$3:$A$8,$A2,'Reconciliation'!$B$3:$B$8,$D2)*$H2/SUMIFS('Agent-User Daily'!$H$2:$H$8,'Agent-User Daily'!$A$2:$A$8,$A2,'Agent-User Daily'!$D$2:$D$8,$D2),0) | H2: 40 | I2: 0 | J2: Finance Sandbox | K2: Prepaid capacity | L2: Finance | M2: Copilot Studio | N2: agent-fin-0001 | O2: u-dana | P2: env-fin
A3: 46294 | B3: HR Assistant | C3: carol@contoso.com | D3: HR-PAYG | E3: =H3+I3 | F3: =H3*Settings!$B$3 | G3: =IFERROR(SUMIFS('Reconciliation'!$E$3:$E$8,'Reconciliation'!$A$3:$A$8,$A3,'Reconciliation'!$B$3:$B$8,$D3)*$H3/SUMIFS('Agent-User Daily'!$H$2:$H$8,'Agent-User Daily'!$A$2:$A$8,$A3,'Agent-User Daily'!$D$2:$D$8,$D3),0) | H3: 0 | I3: 12 | J3: HR Production | K3: Non-billable | L3: Human Resources | M3: Copilot Studio | N3: agent-hr-0001 | O3: u-carol | P3: env-hr
A4: 46295 | B4: HR Assistant | C4: alice@contoso.com | D4: HR-PAYG | E4: =H4+I4 | F4: =H4*Settings!$B$3 | G4: =IFERROR(SUMIFS('Reconciliation'!$E$3:$E$8,'Reconciliation'!$A$3:$A$8,$A4,'Reconciliation'!$B$3:$B$8,$D4)*$H4/SUMIFS('Agent-User Daily'!$H$2:$H$8,'Agent-User Daily'!$A$2:$A$8,$A4,'Agent-User Daily'!$D$2:$D$8,$D4),0) | H4: 125 | I4: 0 | J4: HR Production | K4: PAYG | L4: Human Resources | M4: Copilot Studio | N4: agent-hr-0001 | O4: u-alice | P4: env-hr
A5: 46295 | B5: HR Assistant | C5: bob@contoso.com | D5: HR-PAYG | E5: =H5+I5 | F5: =H5*Settings!$B$3 | G5: =IFERROR(SUMIFS('Reconciliation'!$E$3:$E$8,'Reconciliation'!$A$3:$A$8,$A5,'Reconciliation'!$B$3:$B$8,$D5)*$H5/SUMIFS('Agent-User Daily'!$H$2:$H$8,'Agent-User Daily'!$A$2:$A$8,$A5,'Agent-User Daily'!$D$2:$D$8,$D5),0) | H5: 87 | I5: 0 | J5: HR Production | K5: PAYG | L5: Human Resources | M5: Copilot Studio | N5: agent-hr-0001 | O5: u-bob | P5: env-hr
A6: 46295 | B6: IT Helpdesk Agent | C6: helpdesk@contoso.com | D6: IT-PAYG | E6: =H6+I6 | F6: =H6*Settings!$B$3 | G6: =IFERROR(SUMIFS('Reconciliation'!$E$3:$E$8,'Reconciliation'!$A$3:$A$8,$A6,'Reconciliation'!$B$3:$B$8,$D6)*$H6/SUMIFS('Agent-User Daily'!$H$2:$H$8,'Agent-User Daily'!$A$2:$A$8,$A6,'Agent-User Daily'!$D$2:$D$8,$D6),0) | H6: 980 | I6: 0 | J6: IT Production | K6: PAYG | L6: IT | M6: Copilot Studio | N6: agent-it-0001 | O6: u-helpdesk | P6: env-it
A7: 46295 | B7: Sales Assistant | C7: john@contoso.com | D7: SALES-PAYG | E7: =H7+I7 | F7: =H7*Settings!$B$3 | G7: =IFERROR(SUMIFS('Reconciliation'!$E$3:$E$8,'Reconciliation'!$A$3:$A$8,$A7,'Reconciliation'!$B$3:$B$8,$D7)*$H7/SUMIFS('Agent-User Daily'!$H$2:$H$8,'Agent-User Daily'!$A$2:$A$8,$A7,'Agent-User Daily'!$D$2:$D$8,$D7),0) | H7: 320 | I7: 0 | J7: Sales Production | K7: PAYG | L7: Sales | M7: Copilot Studio | N7: agent-sales-0001 | O7: u-john | P7: env-sales
A8: 46295 | B8: Sales Assistant | C8: mary@contoso.com | D8: SALES-PAYG | E8: =H8+I8 | F8: =H8*Settings!$B$3 | G8: =IFERROR(SUMIFS('Reconciliation'!$E$3:$E$8,'Reconciliation'!$A$3:$A$8,$A8,'Reconciliation'!$B$3:$B$8,$D8)*$H8/SUMIFS('Agent-User Daily'!$H$2:$H$8,'Agent-User Daily'!$A$2:$A$8,$A8,'Agent-User Daily'!$D$2:$D$8,$D8),0) | H8: 145 | I8: 0 | J8: Sales Production | K8: PAYG | L8: Sales | M8: Copilot Studio | N8: agent-sales-0001 | O8: u-mary | P8: env-sales

Sheet M365 Copilot Chat
A1: Period Start | B1: Period End | C1: Agent Name | D1: User | E1: Billing Policy | F1: Credits | G1: Estimated Cost (USD) | H1: Allocated Azure Cost (USD) | I1: Window (days) | J1: Last Activity (UTC) | K1: Department | L1: Agent ID | M1: Billing Policy ID | N1: Source File
A2: 46289 | B2: 46295 | C2: Policy Finder | D2: dana@contoso.com | E2: M365-HR-PAYG | F2: 36 | G2: =F2*Settings!$B$3 | H2: =IFERROR(SUMIFS('Reconciliation'!$E$3:$E$8,'Reconciliation'!$B$3:$B$8,$E2,'Reconciliation'!$A$3:$A$8,">="&$A2,'Reconciliation'!$A$3:$A$8,"<="&$B2)*$F2/SUMIFS('M365 Copilot Chat'!$F$2:$F$5,'M365 Copilot Chat'!$E$2:$E$5,$E2,'M365 Copilot Chat'!$A$2:$A$5,$A2,'M365 Copilot Chat'!$B$2:$B$5,$B2),0) | I2: 7 | J2: 46295 | K2: Finance | L2: P_11111111-aaaa-4bbb-8ccc-000000000002 | M2: 00000000-0000-4000-8000-0000000000a1 | N2: m365_credits_users_and_agents_sample.csv
A3: 46289 | B3: 46295 | C3: Policy Finder | D3: farah@contoso.com | E3: M365-SALES-PAYG | F3: 60 | G3: =F3*Settings!$B$3 | H3: =IFERROR(SUMIFS('Reconciliation'!$E$3:$E$8,'Reconciliation'!$B$3:$B$8,$E3,'Reconciliation'!$A$3:$A$8,">="&$A3,'Reconciliation'!$A$3:$A$8,"<="&$B3)*$F3/SUMIFS('M365 Copilot Chat'!$F$2:$F$5,'M365 Copilot Chat'!$E$2:$E$5,$E3,'M365 Copilot Chat'!$A$2:$A$5,$A3,'M365 Copilot Chat'!$B$2:$B$5,$B3),0) | I3: 7 | J3: 46293 | K3: Sales | L3: P_11111111-aaaa-4bbb-8ccc-000000000002 | M3: 00000000-0000-4000-8000-0000000000b2 | N3: m365_credits_users_and_agents_sample.csv
A4: 46289 | B4: 46295 | C4: Writing Coach | D4: dana@contoso.com | E4: M365-HR-PAYG | F4: 48 | G4: =F4*Settings!$B$3 | H4: =IFERROR(SUMIFS('Reconciliation'!$E$3:$E$8,'Reconciliation'!$B$3:$B$8,$E4,'Reconciliation'!$A$3:$A$8,">="&$A4,'Reconciliation'!$A$3:$A$8,"<="&$B4)*$F4/SUMIFS('M365 Copilot Chat'!$F$2:$F$5,'M365 Copilot Chat'!$E$2:$E$5,$E4,'M365 Copilot Chat'!$A$2:$A$5,$A4,'M365 Copilot Chat'!$B$2:$B$5,$B4),0) | I4: 7 | J4: 46294 | K4: Finance | L4: P_11111111-aaaa-4bbb-8ccc-000000000001 | M4: 00000000-0000-4000-8000-0000000000a1 | N4: m365_credits_users_and_agents_sample.csv
A5: 46289 | B5: 46295 | C5: Writing Coach | D5: eli@contoso.com | E5: M365-HR-PAYG | F5: 24 | G5: =F5*Settings!$B$3 | H5: =IFERROR(SUMIFS('Reconciliation'!$E$3:$E$8,'Reconciliation'!$B$3:$B$8,$E5,'Reconciliation'!$A$3:$A$8,">="&$A5,'Reconciliation'!$A$3:$A$8,"<="&$B5)*$F5/SUMIFS('M365 Copilot Chat'!$F$2:$F$5,'M365 Copilot Chat'!$E$2:$E$5,$E5,'M365 Copilot Chat'!$A$2:$A$5,$A5,'M365 Copilot Chat'!$B$2:$B$5,$B5),0) | I5: 7 | J5: 46292 | K5: Marketing | L5: P_11111111-aaaa-4bbb-8ccc-000000000001 | M5: 00000000-0000-4000-8000-0000000000a1 | N5: m365_credits_users_and_agents_sample.csv

Sheet Feature Detail
A1: Date | B1: Environment | C1: Agent Name | D1: User | E1: Feature | F1: Credits Consumed | G1: Billed Credits | H1: Non-billable Credits | I1: Estimated Cost (USD) | J1: Agent ID | K1: User ID
A2: 46294 | B2: Finance Sandbox | C2: Finance Q&A | D2: dana@contoso.com | E2: Generative answer | F2: =G2+H2 | G2: 40 | H2: 0 | I2: =G2*Settings!$B$3 | J2: agent-fin-0001 | K2: u-dana
A3: 46294 | B3: HR Production | C3: HR Assistant | D3: carol@contoso.com | E3: Generative answer | F3: =G3+H3 | G3: 0 | H3: 12 | I3: =G3*Settings!$B$3 | J3: agent-hr-0001 | K3: u-carol
A4: 46295 | B4: HR Production | C4: HR Assistant | D4: alice@contoso.com | E4: Classic answer | F4: =G4+H4 | G4: 25 | H4: 0 | I4: =G4*Settings!$B$3 | J4: agent-hr-0001 | K4: u-alice
A5: 46295 | B5: HR Production | C5: HR Assistant | D5: alice@contoso.com | E5: Generative answer | F5: =G5+H5 | G5: 100 | H5: 0 | I5: =G5*Settings!$B$3 | J5: agent-hr-0001 | K5: u-alice
A6: 46295 | B6: HR Production | C6: HR Assistant | D6: bob@contoso.com | E6: Classic answer | F6: =G6+H6 | G6: 47 | H6: 0 | I6: =G6*Settings!$B$3 | J6: agent-hr-0001 | K6: u-bob
A7: 46295 | B7: HR Production | C7: HR Assistant | D7: bob@contoso.com | E7: Generative answer | F7: =G7+H7 | G7: 40 | H7: 0 | I7: =G7*Settings!$B$3 | J7: agent-hr-0001 | K7: u-bob
A8: 46295 | B8: IT Production | C8: IT Helpdesk Agent | D8: helpdesk@contoso.com | E8: Generative answer | F8: =G8+H8 | G8: 280 | H8: 0 | I8: =G8*Settings!$B$3 | J8: agent-it-0001 | K8: u-helpdesk
A9: 46295 | B9: IT Production | C9: IT Helpdesk Agent | D9: helpdesk@contoso.com | E9: Tenant graph grounding | F9: =G9+H9 | G9: 700 | H9: 0 | I9: =G9*Settings!$B$3 | J9: agent-it-0001 | K9: u-helpdesk
A10: 46295 | B10: Sales Production | C10: Sales Assistant | D10: john@contoso.com | E10: Agent action | F10: =G10+H10 | G10: 250 | H10: 0 | I10: =G10*Settings!$B$3 | J10: agent-sales-0001 | K10: u-john
A11: 46295 | B11: Sales Production | C11: Sales Assistant | D11: john@contoso.com | E11: Generative answer | F11: =G11+H11 | G11: 70 | H11: 0 | I11: =G11*Settings!$B$3 | J11: agent-sales-0001 | K11: u-john
A12: 46295 | B12: Sales Production | C12: Sales Assistant | D12: mary@contoso.com | E12: Generative answer | F12: =G12+H12 | G12: 145 | H12: 0 | I12: =G12*Settings!$B$3 | J12: agent-sales-0001 | K12: u-mary

Sheet Agent Summary
A1: Product | B1: Agent Name | C1: Environment | D1: Billing Policy | E1: Credits Consumed | F1: Billed Credits | G1: Non-billable Credits | H1: Estimated Cost (USD) | I1: Allocated Azure Cost (USD) | J1: Distinct Users | K1: Agent ID
A2: Copilot Studio | B2: Finance Q&A | C2: Finance Sandbox | D2: (none) | E2: =SUMIFS('Agent-User Daily'!$E$2:$E$8,'Agent-User Daily'!$N$2:$N$8,$K2) | F2: =SUMIFS('Agent-User Daily'!$H$2:$H$8,'Agent-User Daily'!$N$2:$N$8,$K2) | G2: =SUMIFS('Agent-User Daily'!$I$2:$I$8,'Agent-User Daily'!$N$2:$N$8,$K2) | H2: =SUMIFS('Agent-User Daily'!$F$2:$F$8,'Agent-User Daily'!$N$2:$N$8,$K2) | I2: =SUMIFS('Agent-User Daily'!$G$2:$G$8,'Agent-User Daily'!$N$2:$N$8,$K2) | J2: 1 | K2: agent-fin-0001
A3: Copilot Studio | B3: HR Assistant | C3: HR Production | D3: HR-PAYG | E3: =SUMIFS('Agent-User Daily'!$E$2:$E$8,'Agent-User Daily'!$N$2:$N$8,$K3) | F3: =SUMIFS('Agent-User Daily'!$H$2:$H$8,'Agent-User Daily'!$N$2:$N$8,$K3) | G3: =SUMIFS('Agent-User Daily'!$I$2:$I$8,'Agent-User Daily'!$N$2:$N$8,$K3) | H3: =SUMIFS('Agent-User Daily'!$F$2:$F$8,'Agent-User Daily'!$N$2:$N$8,$K3) | I3: =SUMIFS('Agent-User Daily'!$G$2:$G$8,'Agent-User Daily'!$N$2:$N$8,$K3) | J3: 3 | K3: agent-hr-0001
A4: Copilot Studio | B4: IT Helpdesk Agent | C4: IT Production | D4: IT-PAYG | E4: =SUMIFS('Agent-User Daily'!$E$2:$E$8,'Agent-User Daily'!$N$2:$N$8,$K4) | F4: =SUMIFS('Agent-User Daily'!$H$2:$H$8,'Agent-User Daily'!$N$2:$N$8,$K4) | G4: =SUMIFS('Agent-User Daily'!$I$2:$I$8,'Agent-User Daily'!$N$2:$N$8,$K4) | H4: =SUMIFS('Agent-User Daily'!$F$2:$F$8,'Agent-User Daily'!$N$2:$N$8,$K4) | I4: =SUMIFS('Agent-User Daily'!$G$2:$G$8,'Agent-User Daily'!$N$2:$N$8,$K4) | J4: 1 | K4: agent-it-0001
A5: Copilot Studio | B5: Sales Assistant | C5: Sales Production | D5: SALES-PAYG | E5: =SUMIFS('Agent-User Daily'!$E$2:$E$8,'Agent-User Daily'!$N$2:$N$8,$K5) | F5: =SUMIFS('Agent-User Daily'!$H$2:$H$8,'Agent-User Daily'!$N$2:$N$8,$K5) | G5: =SUMIFS('Agent-User Daily'!$I$2:$I$8,'Agent-User Daily'!$N$2:$N$8,$K5) | H5: =SUMIFS('Agent-User Daily'!$F$2:$F$8,'Agent-User Daily'!$N$2:$N$8,$K5) | I5: =SUMIFS('Agent-User Daily'!$G$2:$G$8,'Agent-User Daily'!$N$2:$N$8,$K5) | J5: 2 | K5: agent-sales-0001
A6: Microsoft 365 Copilot Chat (metered agents) | B6: Policy Finder | D6: (multiple) | E6: =SUMIFS('M365 Copilot Chat'!$F$2:$F$5,'M365 Copilot Chat'!$L$2:$L$5,$K6) | F6: =E6 | G6: 0 | H6: =SUMIFS('M365 Copilot Chat'!$G$2:$G$5,'M365 Copilot Chat'!$L$2:$L$5,$K6) | I6: =SUMIFS('M365 Copilot Chat'!$H$2:$H$5,'M365 Copilot Chat'!$L$2:$L$5,$K6) | J6: 2 | K6: P_11111111-aaaa-4bbb-8ccc-000000000002
A7: Microsoft 365 Copilot Chat (metered agents) | B7: Writing Coach | D7: M365-HR-PAYG | E7: =SUMIFS('M365 Copilot Chat'!$F$2:$F$5,'M365 Copilot Chat'!$L$2:$L$5,$K7) | F7: =E7 | G7: 0 | H7: =SUMIFS('M365 Copilot Chat'!$G$2:$G$5,'M365 Copilot Chat'!$L$2:$L$5,$K7) | I7: =SUMIFS('M365 Copilot Chat'!$H$2:$H$5,'M365 Copilot Chat'!$L$2:$L$5,$K7) | J7: 2 | K7: P_11111111-aaaa-4bbb-8ccc-000000000001
A8: Total | E8: =SUM(E2:E7) | F8: =SUM(F2:F7) | G8: =SUM(G2:G7) | H8: =SUM(H2:H7) | I8: =SUM(I2:I7)

Sheet User Summary
A1: User | B1: Display Name | C1: Department | D1: Copilot Studio Credits | E1: M365 Copilot Chat Credits | F1: Billed Credits | G1: Non-billable Credits | H1: Estimated Cost (USD) | I1: Allocated Azure Cost (USD) | J1: Agents Used
A2: alice@contoso.com | B2: Alice Anders | C2: Human Resources | D2: =SUMIFS('Agent-User Daily'!$E$2:$E$8,'Agent-User Daily'!$C$2:$C$8,$A2) | E2: =SUMIFS('M365 Copilot Chat'!$F$2:$F$5,'M365 Copilot Chat'!$D$2:$D$5,$A2) | F2: =SUMIFS('Agent-User Daily'!$H$2:$H$8,'Agent-User Daily'!$C$2:$C$8,$A2)+E2 | G2: =SUMIFS('Agent-User Daily'!$I$2:$I$8,'Agent-User Daily'!$C$2:$C$8,$A2) | H2: =SUMIFS('Agent-User Daily'!$F$2:$F$8,'Agent-User Daily'!$C$2:$C$8,$A2)+SUMIFS('M365 Copilot Chat'!$G$2:$G$5,'M365 Copilot Chat'!$D$2:$D$5,$A2) | I2: =SUMIFS('Agent-User Daily'!$G$2:$G$8,'Agent-User Daily'!$C$2:$C$8,$A2)+SUMIFS('M365 Copilot Chat'!$H$2:$H$5,'M365 Copilot Chat'!$D$2:$D$5,$A2) | J2: 1
A3: bob@contoso.com | B3: Bob Brown | C3: Human Resources | D3: =SUMIFS('Agent-User Daily'!$E$2:$E$8,'Agent-User Daily'!$C$2:$C$8,$A3) | E3: =SUMIFS('M365 Copilot Chat'!$F$2:$F$5,'M365 Copilot Chat'!$D$2:$D$5,$A3) | F3: =SUMIFS('Agent-User Daily'!$H$2:$H$8,'Agent-User Daily'!$C$2:$C$8,$A3)+E3 | G3: =SUMIFS('Agent-User Daily'!$I$2:$I$8,'Agent-User Daily'!$C$2:$C$8,$A3) | H3: =SUMIFS('Agent-User Daily'!$F$2:$F$8,'Agent-User Daily'!$C$2:$C$8,$A3)+SUMIFS('M365 Copilot Chat'!$G$2:$G$5,'M365 Copilot Chat'!$D$2:$D$5,$A3) | I3: =SUMIFS('Agent-User Daily'!$G$2:$G$8,'Agent-User Daily'!$C$2:$C$8,$A3)+SUMIFS('M365 Copilot Chat'!$H$2:$H$5,'M365 Copilot Chat'!$D$2:$D$5,$A3) | J3: 1
A4: carol@contoso.com | B4: Carol Chen | C4: Human Resources | D4: =SUMIFS('Agent-User Daily'!$E$2:$E$8,'Agent-User Daily'!$C$2:$C$8,$A4) | E4: =SUMIFS('M365 Copilot Chat'!$F$2:$F$5,'M365 Copilot Chat'!$D$2:$D$5,$A4) | F4: =SUMIFS('Agent-User Daily'!$H$2:$H$8,'Agent-User Daily'!$C$2:$C$8,$A4)+E4 | G4: =SUMIFS('Agent-User Daily'!$I$2:$I$8,'Agent-User Daily'!$C$2:$C$8,$A4) | H4: =SUMIFS('Agent-User Daily'!$F$2:$F$8,'Agent-User Daily'!$C$2:$C$8,$A4)+SUMIFS('M365 Copilot Chat'!$G$2:$G$5,'M365 Copilot Chat'!$D$2:$D$5,$A4) | I4: =SUMIFS('Agent-User Daily'!$G$2:$G$8,'Agent-User Daily'!$C$2:$C$8,$A4)+SUMIFS('M365 Copilot Chat'!$H$2:$H$5,'M365 Copilot Chat'!$D$2:$D$5,$A4) | J4: 1
A5: dana@contoso.com | B5: Dana Diaz | C5: Finance | D5: =SUMIFS('Agent-User Daily'!$E$2:$E$8,'Agent-User Daily'!$C$2:$C$8,$A5) | E5: =SUMIFS('M365 Copilot Chat'!$F$2:$F$5,'M365 Copilot Chat'!$D$2:$D$5,$A5) | F5: =SUMIFS('Agent-User Daily'!$H$2:$H$8,'Agent-User Daily'!$C$2:$C$8,$A5)+E5 | G5: =SUMIFS('Agent-User Daily'!$I$2:$I$8,'Agent-User Daily'!$C$2:$C$8,$A5) | H5: =SUMIFS('Agent-User Daily'!$F$2:$F$8,'Agent-User Daily'!$C$2:$C$8,$A5)+SUMIFS('M365 Copilot Chat'!$G$2:$G$5,'M365 Copilot Chat'!$D$2:$D$5,$A5) | I5: =SUMIFS('Agent-User Daily'!$G$2:$G$8,'Agent-User Daily'!$C$2:$C$8,$A5)+SUMIFS('M365 Copilot Chat'!$H$2:$H$5,'M365 Copilot Chat'!$D$2:$D$5,$A5) | J5: 3
A6: eli@contoso.com | B6: Eli Evans | C6: Marketing | D6: =SUMIFS('Agent-User Daily'!$E$2:$E$8,'Agent-User Daily'!$C$2:$C$8,$A6) | E6: =SUMIFS('M365 Copilot Chat'!$F$2:$F$5,'M365 Copilot Chat'!$D$2:$D$5,$A6) | F6: =SUMIFS('Agent-User Daily'!$H$2:$H$8,'Agent-User Daily'!$C$2:$C$8,$A6)+E6 | G6: =SUMIFS('Agent-User Daily'!$I$2:$I$8,'Agent-User Daily'!$C$2:$C$8,$A6) | H6: =SUMIFS('Agent-User Daily'!$F$2:$F$8,'Agent-User Daily'!$C$2:$C$8,$A6)+SUMIFS('M365 Copilot Chat'!$G$2:$G$5,'M365 Copilot Chat'!$D$2:$D$5,$A6) | I6: =SUMIFS('Agent-User Daily'!$G$2:$G$8,'Agent-User Daily'!$C$2:$C$8,$A6)+SUMIFS('M365 Copilot Chat'!$H$2:$H$5,'M365 Copilot Chat'!$D$2:$D$5,$A6) | J6: 1
A7: farah@contoso.com | B7: Farah Fox | C7: Sales | D7: =SUMIFS('Agent-User Daily'!$E$2:$E$8,'Agent-User Daily'!$C$2:$C$8,$A7) | E7: =SUMIFS('M365 Copilot Chat'!$F$2:$F$5,'M365 Copilot Chat'!$D$2:$D$5,$A7) | F7: =SUMIFS('Agent-User Daily'!$H$2:$H$8,'Agent-User Daily'!$C$2:$C$8,$A7)+E7 | G7: =SUMIFS('Agent-User Daily'!$I$2:$I$8,'Agent-User Daily'!$C$2:$C$8,$A7) | H7: =SUMIFS('Agent-User Daily'!$F$2:$F$8,'Agent-User Daily'!$C$2:$C$8,$A7)+SUMIFS('M365 Copilot Chat'!$G$2:$G$5,'M365 Copilot Chat'!$D$2:$D$5,$A7) | I7: =SUMIFS('Agent-User Daily'!$G$2:$G$8,'Agent-User Daily'!$C$2:$C$8,$A7)+SUMIFS('M365 Copilot Chat'!$H$2:$H$5,'M365 Copilot Chat'!$D$2:$D$5,$A7) | J7: 1
A8: helpdesk@contoso.com | B8: IT Helpdesk | C8: IT | D8: =SUMIFS('Agent-User Daily'!$E$2:$E$8,'Agent-User Daily'!$C$2:$C$8,$A8) | E8: =SUMIFS('M365 Copilot Chat'!$F$2:$F$5,'M365 Copilot Chat'!$D$2:$D$5,$A8) | F8: =SUMIFS('Agent-User Daily'!$H$2:$H$8,'Agent-User Daily'!$C$2:$C$8,$A8)+E8 | G8: =SUMIFS('Agent-User Daily'!$I$2:$I$8,'Agent-User Daily'!$C$2:$C$8,$A8) | H8: =SUMIFS('Agent-User Daily'!$F$2:$F$8,'Agent-User Daily'!$C$2:$C$8,$A8)+SUMIFS('M365 Copilot Chat'!$G$2:$G$5,'M365 Copilot Chat'!$D$2:$D$5,$A8) | I8: =SUMIFS('Agent-User Daily'!$G$2:$G$8,'Agent-User Daily'!$C$2:$C$8,$A8)+SUMIFS('M365 Copilot Chat'!$H$2:$H$5,'M365 Copilot Chat'!$D$2:$D$5,$A8) | J8: 1
A9: john@contoso.com | B9: John Jones | C9: Sales | D9: =SUMIFS('Agent-User Daily'!$E$2:$E$8,'Agent-User Daily'!$C$2:$C$8,$A9) | E9: =SUMIFS('M365 Copilot Chat'!$F$2:$F$5,'M365 Copilot Chat'!$D$2:$D$5,$A9) | F9: =SUMIFS('Agent-User Daily'!$H$2:$H$8,'Agent-User Daily'!$C$2:$C$8,$A9)+E9 | G9: =SUMIFS('Agent-User Daily'!$I$2:$I$8,'Agent-User Daily'!$C$2:$C$8,$A9) | H9: =SUMIFS('Agent-User Daily'!$F$2:$F$8,'Agent-User Daily'!$C$2:$C$8,$A9)+SUMIFS('M365 Copilot Chat'!$G$2:$G$5,'M365 Copilot Chat'!$D$2:$D$5,$A9) | I9: =SUMIFS('Agent-User Daily'!$G$2:$G$8,'Agent-User Daily'!$C$2:$C$8,$A9)+SUMIFS('M365 Copilot Chat'!$H$2:$H$5,'M365 Copilot Chat'!$D$2:$D$5,$A9) | J9: 1
A10: mary@contoso.com | B10: Mary Miller | C10: Sales | D10: =SUMIFS('Agent-User Daily'!$E$2:$E$8,'Agent-User Daily'!$C$2:$C$8,$A10) | E10: =SUMIFS('M365 Copilot Chat'!$F$2:$F$5,'M365 Copilot Chat'!$D$2:$D$5,$A10) | F10: =SUMIFS('Agent-User Daily'!$H$2:$H$8,'Agent-User Daily'!$C$2:$C$8,$A10)+E10 | G10: =SUMIFS('Agent-User Daily'!$I$2:$I$8,'Agent-User Daily'!$C$2:$C$8,$A10) | H10: =SUMIFS('Agent-User Daily'!$F$2:$F$8,'Agent-User Daily'!$C$2:$C$8,$A10)+SUMIFS('M365 Copilot Chat'!$G$2:$G$5,'M365 Copilot Chat'!$D$2:$D$5,$A10) | I10: =SUMIFS('Agent-User Daily'!$G$2:$G$8,'Agent-User Daily'!$C$2:$C$8,$A10)+SUMIFS('M365 Copilot Chat'!$H$2:$H$5,'M365 Copilot Chat'!$D$2:$D$5,$A10) | J10: 1
A11: Total | D11: =SUM(D2:D10) | E11: =SUM(E2:E10) | F11: =SUM(F2:F10) | G11: =SUM(G2:G10) | H11: =SUM(H2:H10) | I11: =SUM(I2:I10)

Sheet Feature Summary
A1: Feature | B1: Credits Consumed | C1: Billed Credits | D1: Non-billable Credits | E1: Estimated Cost (USD)
A2: Agent action | B2: =SUMIFS('Feature Detail'!$F$2:$F$12,'Feature Detail'!$E$2:$E$12,$A2) | C2: =SUMIFS('Feature Detail'!$G$2:$G$12,'Feature Detail'!$E$2:$E$12,$A2) | D2: =SUMIFS('Feature Detail'!$H$2:$H$12,'Feature Detail'!$E$2:$E$12,$A2) | E2: =SUMIFS('Feature Detail'!$I$2:$I$12,'Feature Detail'!$E$2:$E$12,$A2)
A3: Classic answer | B3: =SUMIFS('Feature Detail'!$F$2:$F$12,'Feature Detail'!$E$2:$E$12,$A3) | C3: =SUMIFS('Feature Detail'!$G$2:$G$12,'Feature Detail'!$E$2:$E$12,$A3) | D3: =SUMIFS('Feature Detail'!$H$2:$H$12,'Feature Detail'!$E$2:$E$12,$A3) | E3: =SUMIFS('Feature Detail'!$I$2:$I$12,'Feature Detail'!$E$2:$E$12,$A3)
A4: Generative answer | B4: =SUMIFS('Feature Detail'!$F$2:$F$12,'Feature Detail'!$E$2:$E$12,$A4) | C4: =SUMIFS('Feature Detail'!$G$2:$G$12,'Feature Detail'!$E$2:$E$12,$A4) | D4: =SUMIFS('Feature Detail'!$H$2:$H$12,'Feature Detail'!$E$2:$E$12,$A4) | E4: =SUMIFS('Feature Detail'!$I$2:$I$12,'Feature Detail'!$E$2:$E$12,$A4)
A5: Tenant graph grounding | B5: =SUMIFS('Feature Detail'!$F$2:$F$12,'Feature Detail'!$E$2:$E$12,$A5) | C5: =SUMIFS('Feature Detail'!$G$2:$G$12,'Feature Detail'!$E$2:$E$12,$A5) | D5: =SUMIFS('Feature Detail'!$H$2:$H$12,'Feature Detail'!$E$2:$E$12,$A5) | E5: =SUMIFS('Feature Detail'!$I$2:$I$12,'Feature Detail'!$E$2:$E$12,$A5)
A6: Total | B6: =SUM(B2:B5) | C6: =SUM(C2:C5) | D6: =SUM(D2:D5) | E6: =SUM(E2:E5)

Sheet Reconciliation
A1: A. Azure Cost Management - actual charges on Copilot meters, per billing policy per day
A2: Date | B2: Billing Policy (Azure resource) | C2: Meter | D2: Azure Quantity (credits) | E2: Azure Cost (USD) | F2: Report Billed Credits - Copilot Studio (same policy & date) | G2: Difference (credits)
A3: 46292 | B3: M365-HR-PAYG | C3: Microsoft Copilot Studio / Copilot Credit | D3: 50 | E3: 0.5 | F3: =SUMIFS('Agent-User Daily'!$H$2:$H$8,'Agent-User Daily'!$A$2:$A$8,$A3,'Agent-User Daily'!$D$2:$D$8,$B3) | G3: =D3-F3
A4: 46293 | B4: M365-SALES-PAYG | C4: Microsoft Copilot Studio / Copilot Credit | D4: 60 | E4: 0.6 | F4: =SUMIFS('Agent-User Daily'!$H$2:$H$8,'Agent-User Daily'!$A$2:$A$8,$A4,'Agent-User Daily'!$D$2:$D$8,$B4) | G4: =D4-F4
A5: 46294 | B5: M365-HR-PAYG | C5: Microsoft Copilot Studio / Copilot Credit | D5: 60 | E5: 0.6 | F5: =SUMIFS('Agent-User Daily'!$H$2:$H$8,'Agent-User Daily'!$A$2:$A$8,$A5,'Agent-User Daily'!$D$2:$D$8,$B5) | G5: =D5-F5
A6: 46295 | B6: HR-PAYG | C6: Microsoft Copilot Studio / Copilot Credit | D6: 212 | E6: 2.12 | F6: =SUMIFS('Agent-User Daily'!$H$2:$H$8,'Agent-User Daily'!$A$2:$A$8,$A6,'Agent-User Daily'!$D$2:$D$8,$B6) | G6: =D6-F6
A7: 46295 | B7: IT-PAYG | C7: Microsoft Copilot Studio / Copilot Credit | D7: 1000 | E7: 10 | F7: =SUMIFS('Agent-User Daily'!$H$2:$H$8,'Agent-User Daily'!$A$2:$A$8,$A7,'Agent-User Daily'!$D$2:$D$8,$B7) | G7: =D7-F7
A8: 46295 | B8: SALES-PAYG | C8: Microsoft Copilot Studio / Copilot Credit | D8: 465 | E8: 4.65 | F8: =SUMIFS('Agent-User Daily'!$H$2:$H$8,'Agent-User Daily'!$A$2:$A$8,$A8,'Agent-User Daily'!$D$2:$D$8,$B8) | G8: =D8-F8
A10: A2. Microsoft 365 billing policies - Copilot Credits report window vs Azure
A11: Billing Policy | B11: Period Start | C11: Period End | D11: Report Credits (M365 export) | E11: Azure Quantity (same policy & window) | F11: Difference (credits)
A12: M365-HR-PAYG | B12: 46289 | C12: 46295 | D12: =SUMIFS('M365 Copilot Chat'!$F$2:$F$5,'M365 Copilot Chat'!$E$2:$E$5,$A12,'M365 Copilot Chat'!$A$2:$A$5,$B12,'M365 Copilot Chat'!$B$2:$B$5,$C12) | E12: =SUMIFS($D$3:$D$8,$B$3:$B$8,$A12,$A$3:$A$8,">="&$B12,$A$3:$A$8,"<="&$C12) | F12: =E12-D12
A13: M365-SALES-PAYG | B13: 46289 | C13: 46295 | D13: =SUMIFS('M365 Copilot Chat'!$F$2:$F$5,'M365 Copilot Chat'!$E$2:$E$5,$A13,'M365 Copilot Chat'!$A$2:$A$5,$B13,'M365 Copilot Chat'!$B$2:$B$5,$C13) | E13: =SUMIFS($D$3:$D$8,$B$3:$B$8,$A13,$A$3:$A$8,">="&$B13,$A$3:$A$8,"<="&$C13) | F13: =E13-D13
A15: B. Environments (Power Platform licensing API)
A16: Environment | B16: Billing Policy | C16: Copilot Studio PAYG enabled on policy | D16: Prepaid Credits Allocated | E16: Billed Credits - prepaid (last snapshot) | F16: Billed Credits - PAYG (last snapshot) | G16: Snapshot Date
A17: HR Production | B17: HR-PAYG | C17: Yes | D17: 0
A18: Sales Production | B18: SALES-PAYG | C18: Yes | D18: 0
A19: IT Production | B19: IT-PAYG | C19: Yes | D19: 0
A20: Finance Sandbox | B20: (none) | C20: No | D20: 5000
A22: C. Tenant Copilot Credit capacity (Power Platform licensing API)
A23: Prepaid credits entitled | B23: 25000
A24: Credits allocated to environments | B24: 5000
A25: Billed credits consumed (MonthToDate) | B25: 40
A26: As of | B26: 2026-09-30

Sheet About
A1: How this report is built
A2: Copilot Studio: Power Platform API (api-version 2024-10-01) - GET /licensing/entitlements/MCSMessages/users and GET /licensing/entitlements/MCSMessages/users/{userId}/resources, queried one day at a time (fromDate = toDate). 'Billed Credits' is the API 'consumed' value; 'Non-billable Credits' is metadata.NonBillableQuantity.
A3: Billing policy and Copilot Studio PAYG flag: GET /licensing/billingPolicies (payGoEntitlements[MCSMessages].payAsYouGoState). Environment names: GET /environmentmanagement/environments. Users: Microsoft Graph $batch.
A4: Microsoft 365 Copilot Chat metered agents: the 'Users and agents' CSV export of the Microsoft 365 admin center Copilot Credits report (Reports > Usage > Microsoft Copilot > Credits). Microsoft offers no API for it.
A5: Actual charges: Azure Cost Management Query API, resource type Microsoft.PowerPlatform/accounts (one resource per billing policy), Copilot meters only. Azure has no agent or user dimension, so it is allocated to report rows.
A6: Limits: Microsoft restricted the agent listing endpoint (/licensing/entitlements/MCSMessages/resources) to the Power Platform admin center in September 2026. Usage with no user identity can't be listed per agent and shows up as Azure cost that is not matched to a report row (see Overview).
A7: The user-level endpoints are in the public REST reference, but Microsoft has said this consumption API family is intended for the Power Platform admin center. Keep the admin center downloads (Licensing > Copilot Studio > Download report) as the fallback.
A8: Latency: licensing snapshots are daily (00:00 UTC) and Azure charges can take 24 hours. Report on days that are at least 2 days old. Validate totals against your Azure invoice before using them for chargeback.
